footsbviz/__init__.py
footsbviz/plots.py
footsbviz-0.2.0.dist-info/METADATA
footsbviz-0.2.0.dist-info/WHEEL
footsbviz-0.2.0.dist-info/licenses/LICENSE
footsbviz-0.2.0.dist-info/RECORD
