Metadata-Version: 2.4
Name: footsbviz
Version: 0.2.0
Summary: Zero-friction visuals for StatsBomb open data (no data engineering).
Project-URL: Homepage, https://github.com/amitbakde99/footsbviz
Project-URL: Issues, https://github.com/amitbakde99/footsbviz/issues
Project-URL: Source, https://github.com/amitbakde99/footsbviz
Author-email: Amit Bakde <amitbakde99@gmail.com>
License: MIT License
License-File: LICENSE
Keywords: analytics,football,soccer,statsbomb,visualization,xG
Requires-Python: >=3.9
Requires-Dist: matplotlib>=3.7
Requires-Dist: numpy>=1.23
Requires-Dist: pandas>=1.5
Requires-Dist: requests>=2.31
Provides-Extra: viz
Requires-Dist: highlight-text>=0.2.0; extra == 'viz'
Requires-Dist: seaborn>=0.12; extra == 'viz'
